tosnativeclient/__init__.py
tosnativeclient/tosnativeclient.cpython-310-darwin.so
tosnativeclient/tosnativeclient.pyi
tosnativeclient-1.1.11.dist-info/METADATA
tosnativeclient-1.1.11.dist-info/WHEEL
tosnativeclient-1.1.11.dist-info/RECORD
