Metadata-Version: 2.4
Name: tosnativeclient
Version: 1.1.11
Classifier: Programming Language :: Rust
Classifier: Programming Language :: Python :: Implementation :: CPython
Classifier: Programming Language :: Python :: Implementation :: PyPy
Classifier: License :: OSI Approved :: Apache Software License
Summary: python native client for tos
Author: xiangshijian
License: Apache-2.0
Requires-Python: >=3.8
